JiraIssueSelector-1.3.3.data/scripts/git-jira
jira_issue_selector/__init__.py
jira_issue_selector/__main__.py
jira_issue_selector/issue_selector.py
jira_issue_selector/jira_issue.py
jira_issue_selector/data/global.conf.example
jira_issue_selector/data/local.conf.example
jira_issue_selector/ui/selector.py
JiraIssueSelector-1.3.3.dist-info/LICENSE.txt
JiraIssueSelector-1.3.3.dist-info/METADATA
JiraIssueSelector-1.3.3.dist-info/WHEEL
JiraIssueSelector-1.3.3.dist-info/top_level.txt
JiraIssueSelector-1.3.3.dist-info/RECORD
