Metadata-Version: 2.1
Name: JiraIssueSelector
Version: 1.3.3
Summary: Allows you to quickly select and prepend JIRA issues to git commit messages
Home-page: https://github.com/berulacks/git-jira-issue-selector
Author: Derin Yarsuvat
Author-email: derin@ml1.net
License: GPLv3
Download-URL: https://github.com/Berulacks/git-jira-issue-selector/releases/download/v1.3.3/JiraIssueSelector-1.3.3-py3-none-any.whl
Platform: UNKNOWN
Requires-Python: >=3
Requires-Dist: blessed (>=1.15)
Requires-Dist: certifi (==2018.4.16)
Requires-Dist: chardet (==3.0.4)
Requires-Dist: fuzzywuzzy (>=0.16.0)
Requires-Dist: gitdb2 (==2.0.3)
Requires-Dist: GitPython (==2.1.9)
Requires-Dist: idna (==2.6)
Requires-Dist: python-Levenshtein (==0.12.0)
Requires-Dist: PyYAML (>=4.2b4)
Requires-Dist: requests (>=2.21.0)
Requires-Dist: six (==1.11.0)
Requires-Dist: smmap2 (==2.0.3)
Requires-Dist: urllib3 (==1.23)
Requires-Dist: wcwidth (==0.1.7)
